eyelink_reader/__init__.py
eyelink_reader/edfdata.py
eyelink_reader/edfdata_containers.py
eyelink_reader/edffile.py
eyelink_reader/data/example.edf
eyelink_reader-0.2.0.dist-info/METADATA
eyelink_reader-0.2.0.dist-info/WHEEL
eyelink_reader-0.2.0.dist-info/licenses/LICENSE
eyelink_reader-0.2.0.dist-info/RECORD
