Metadata-Version: 2.3
Name: eyelink_reader
Version: 0.2.0
Summary: A package to import eye tracking recording generated by SR Research Eyelink eye tracker from EDF-files.
Project-URL: Homepage, https://github.com/alexander-pastukhov/eyelink_reader
Project-URL: Issues, https://github.com/alexander-pastukhov/eyelink_reader/issues
Author-email: "Alexander (Sasha) Pastukhov" <pastukhov.alexander@gmail.com>
Classifier: License :: OSI Approved :: MIT License
Classifier: Operating System :: OS Independent
Classifier: Programming Language :: Python :: 3
Requires-Python: >=3.8
